README.md
setup.py
heuristic.egg-info/PKG-INFO
heuristic.egg-info/SOURCES.txt
heuristic.egg-info/dependency_links.txt
heuristic.egg-info/top_level.txt
pacote1_raiz/__init__.py
pacote1_raiz/heuristica.py
pacote1_raiz/pop.py
pacote1_raiz/abc/__init__.py
pacote1_raiz/abc/abc.py
pacote1_raiz/abc/abc2.py
pacote1_raiz/dragonfly/__init__.py
pacote1_raiz/dragonfly/dragonfly.py
pacote1_raiz/firefly/__init__.py
pacote1_raiz/firefly/firefly.py
pacote1_raiz/pso/__init__.py
pacote1_raiz/pso/pso.py
pacote1_raiz/sa/__init__.py
pacote1_raiz/sa/sa.py
tools/__init__.py
tools/functions.py
tools/mazars.py
tools/plots.py
tools/processing.py